{
    "info": {
        "_postman_id": "store-features-collection-001",
        "name": "Store Features API",
        "description": "Postman/Apidog collection for Store Features API endpoints. All endpoints are public (no authentication required).",
        "schema": "https://schema.getpostman.com/json/collection/v2.1.0/collection.json"
    },
    "item": [
        {
            "name": "Get All Store Features",
            "request": {
                "method": "GET",
                "header": [
                    {
                        "key": "Accept",
                        "value": "application/json",
                        "type": "text"
                    },
                    {
                        "key": "Accept-Language",
                        "value": "en",
                        "type": "text",
                        "description": "Language code: en or ar (optional, defaults to en)"
                    }
                ],
                "url": {
                    "raw": "{{base_url}}/api/v1/store-features?per_page=15",
                    "host": ["{{base_url}}"],
                    "path": ["api", "v1", "store-features"],
                    "query": [
                        {
                            "key": "per_page",
                            "value": "15",
                            "description": "Number of items per page (optional, default: 15)",
                            "disabled": true
                        }
                    ]
                },
                "description": "Get all store features.\n\n**Authentication:** Not required (public endpoint)\n\n**Query Parameters (all optional):**\n- `per_page`: Number of items per page (default: 15)\n\n**Response includes:**\n- Paginated list of store features\n- Each feature includes: id, name (translated), name_en, name_ar, description (translated), description_en, description_ar, image, timestamps"
            },
            "response": [
                {
                    "name": "Success Response",
                    "originalRequest": {
                        "method": "GET",
                        "header": [
                            {
                                "key": "Accept",
                                "value": "application/json"
                            }
                        ],
                        "url": {
                            "raw": "{{base_url}}/api/v1/store-features",
                            "host": ["{{base_url}}"],
                            "path": ["api", "v1", "store-features"]
                        }
                    },
                    "status": "OK",
                    "code": 200,
                    "_postman_previewlanguage": "json",
                    "header": [
                        {
                            "key": "Content-Type",
                            "value": "application/json"
                        }
                    ],
                    "cookie": [],
                    "body": "{\n    \"success\": true,\n    \"message\": \"Store features fetched successfully\",\n    \"data\": [\n        {\n            \"id\": 1,\n            \"name\": \"Fast Delivery\",\n            \"name_en\": \"Fast Delivery\",\n            \"name_ar\": \"توصيل سريع\",\n            \"description\": \"We deliver your orders quickly and efficiently to your doorstep.\",\n            \"description_en\": \"We deliver your orders quickly and efficiently to your doorstep.\",\n            \"description_ar\": \"نوصل طلباتك بسرعة وكفاءة إلى باب منزلك.\",\n            \"image\": \"http://localhost:8000/storage/assets/images/features/fast-delivery.svg\",\n            \"created_at\": \"2025-12-08T11:29:36.000000Z\",\n            \"updated_at\": \"2025-12-08T11:29:36.000000Z\"\n        },\n        {\n            \"id\": 2,\n            \"name\": \"Secure Payment\",\n            \"name_en\": \"Secure Payment\",\n            \"name_ar\": \"دفع آمن\",\n            \"description\": \"Your payment information is protected with the latest security standards.\",\n            \"description_en\": \"Your payment information is protected with the latest security standards.\",\n            \"description_ar\": \"معلومات الدفع الخاصة بك محمية بأحدث معايير الأمان.\",\n            \"image\": \"http://localhost:8000/storage/assets/images/features/secure-payment.svg\",\n            \"created_at\": \"2025-12-08T11:29:36.000000Z\",\n            \"updated_at\": \"2025-12-08T11:29:36.000000Z\"\n        },\n        {\n            \"id\": 3,\n            \"name\": \"Quality Products\",\n            \"name_en\": \"Quality Products\",\n            \"name_ar\": \"منتجات عالية الجودة\",\n            \"description\": \"We offer only the best quality products from trusted suppliers.\",\n            \"description_en\": \"We offer only the best quality products from trusted suppliers.\",\n            \"description_ar\": \"نوفر فقط أفضل المنتجات عالية الجودة من موردين موثوقين.\",\n            \"image\": \"http://localhost:8000/storage/assets/images/features/quality-products.svg\",\n            \"created_at\": \"2025-12-08T11:29:36.000000Z\",\n            \"updated_at\": \"2025-12-08T11:29:36.000000Z\"\n        }\n    ],\n    \"pagination\": {\n        \"current_page\": 1,\n        \"per_page\": 15,\n        \"total\": 6,\n        \"last_page\": 1,\n        \"from\": 1,\n        \"to\": 6\n    }\n}"
                }
            ]
        },
        {
            "name": "Get Single Store Feature",
            "request": {
                "method": "GET",
                "header": [
                    {
                        "key": "Accept",
                        "value": "application/json",
                        "type": "text"
                    },
                    {
                        "key": "Accept-Language",
                        "value": "en",
                        "type": "text",
                        "description": "Language code: en or ar (optional, defaults to en)"
                    }
                ],
                "url": {
                    "raw": "{{base_url}}/api/v1/store-features/1",
                    "host": ["{{base_url}}"],
                    "path": ["api", "v1", "store-features", "1"]
                },
                "description": "Get a single store feature by ID.\n\n**Authentication:** Not required (public endpoint)\n\n**Path Parameters:**\n- `id` (integer, required): The store feature ID\n\n**Response includes:**\n- Store feature details: id, name (translated), name_en, name_ar, description (translated), description_en, description_ar, image, timestamps"
            },
            "response": [
                {
                    "name": "Success Response",
                    "originalRequest": {
                        "method": "GET",
                        "header": [
                            {
                                "key": "Accept",
                                "value": "application/json"
                            }
                        ],
                        "url": {
                            "raw": "{{base_url}}/api/v1/store-features/1",
                            "host": ["{{base_url}}"],
                            "path": ["api", "v1", "store-features", "1"]
                        }
                    },
                    "status": "OK",
                    "code": 200,
                    "_postman_previewlanguage": "json",
                    "header": [
                        {
                            "key": "Content-Type",
                            "value": "application/json"
                        }
                    ],
                    "cookie": [],
                    "body": "{\n    \"success\": true,\n    \"message\": \"Store feature fetched successfully\",\n    \"data\": {\n        \"id\": 1,\n        \"name\": \"Fast Delivery\",\n        \"name_en\": \"Fast Delivery\",\n        \"name_ar\": \"توصيل سريع\",\n        \"description\": \"We deliver your orders quickly and efficiently to your doorstep.\",\n        \"description_en\": \"We deliver your orders quickly and efficiently to your doorstep.\",\n        \"description_ar\": \"نوصل طلباتك بسرعة وكفاءة إلى باب منزلك.\",\n        \"image\": \"http://localhost:8000/storage/assets/images/features/fast-delivery.svg\",\n        \"created_at\": \"2025-12-08T11:29:36.000000Z\",\n        \"updated_at\": \"2025-12-08T11:29:36.000000Z\"\n    }\n}"
                },
                {
                    "name": "Not Found",
                    "originalRequest": {
                        "method": "GET",
                        "header": [],
                        "url": {
                            "raw": "{{base_url}}/api/v1/store-features/999",
                            "host": ["{{base_url}}"],
                            "path": ["api", "v1", "store-features", "999"]
                        }
                    },
                    "status": "Not Found",
                    "code": 404,
                    "_postman_previewlanguage": "json",
                    "header": [
                        {
                            "key": "Content-Type",
                            "value": "application/json"
                        }
                    ],
                    "cookie": [],
                    "body": "{\n    \"success\": false,\n    \"message\": \"Store feature not found\",\n    \"data\": null\n}"
                }
            ]
        }
    ],
    "event": [
        {
            "listen": "prerequest",
            "script": {
                "type": "text/javascript",
                "exec": [""]
            }
        },
        {
            "listen": "test",
            "script": {
                "type": "text/javascript",
                "exec": [""]
            }
        }
    ],
    "variable": [
        {
            "key": "base_url",
            "value": "http://localhost:8000",
            "type": "string"
        }
    ]
}

